stats_code/__main__.py
stats_code/counter.py
stats_code/counter_worker.py
stats_code/language_config.py
stats_code/py.typed
stats_code/render.py
stats_code/result.py
stats_code/utils.py
stats_code/config/default.yml
stats_code-0.1.5.dist-info/licenses/LICENSE
stats_code-0.1.5.dist-info/METADATA
stats_code-0.1.5.dist-info/WHEEL
stats_code-0.1.5.dist-info/entry_points.txt
stats_code-0.1.5.dist-info/top_level.txt
stats_code-0.1.5.dist-info/RECORD
