Metadata-Version: 2.4
Name: stats-code
Version: 0.1.5
Summary: A full python tool to gather statistics from your codebase.
Author-email: LKLLL <13263311018@163.com>
License:                                  Apache License
Project-URL: Home, https://github.com/LKLLLLLLLLLL/CodeStatistics
Keywords: code,developer,statistics,stats-code
Classifier: Programming Language :: Python :: 3
Classifier: Programming Language :: Python :: 3 :: Only
Classifier: License :: OSI Approved :: Apache Software License
Classifier: Operating System :: OS Independent
Requires-Python: >=3.11
License-File: LICENSE
Requires-Dist: chardet>=5.2.0
Requires-Dist: pathspec>=0.12.1
Requires-Dist: pyyaml>=6.0.3
Requires-Dist: rich>=14.2.0
Dynamic: license-file
